staticpreprocessor
