Metadata-Version: 1.1
Name: django-staticpreprocessor
Version: 0.1.5
Summary: Pre-process static files in Django
Home-page: http://github.com/lpomfrey/django-staticpreprocessor
Author: Luke Pomfrey
Author-email: lpomfrey@gmail.com
License: BSD
Platform: UNKNOWN
Classifier: Development Status :: 4 - Beta
Classifier: Environment :: Web Environment
Classifier: Framework :: Django
Classifier: Intended Audience :: Developers
Classifier: License :: OSI Approved :: BSD License
Classifier: Operating System :: OS Independent
Classifier: Programming Language :: Python
Classifier: Topic :: Internet :: WWW/HTTP
